src/fifo.sv
`default_nettype none
`timescale 1ns/1ns

module fifo #(
    parameter DATA_WIDTH = 32,
    parameter DEPTH = 32
) (
    input  logic clk,
    input  logic rst_n,
    input  logic write_en, //write enable
    input  logic read_en, //read enable
    input  logic [DATA_WIDTH-1:0] data_in,
    output logic [DATA_WIDTH-1:0] data_out,
    output logic full,
    output logic empty
);

logic [DATA_WIDTH-1:0] fifo_mem [0:DEPTH-1];

localparam PTR_W = $clog2(DEPTH);
logic [PTR_W-1:0] write_ptr, read_ptr; // head is write, tail is read

always @(posedge clk or negedge rst_n) begin
    if (rst_n) begin 
        write_ptr <= 0;
        read_ptr <= 0;
    end
    else begin
        if (write_en && !full) begin
            fifo_mem [write_ptr] <= data_in;
            write_ptr <= write_ptr + 1;
        end

        if (read_en && !empty) begin
            data_out <= fifo_mem [read_ptr];
            read_ptr <= read_ptr + 1;
        end
    end
end

assign full = (write_ptr == read_ptr + DEPTH-1);
assign empty = (write_ptr == read_ptr);

endmodule

waveforms/fifo.vcd
$date
	Sat Apr 19 13:42:42 2025
$end
$version
	Icarus Verilog
$end
$timescale
	1ns
$end
$scope module fifo $end
$var wire 1 ! clk $end
$var wire 32 " data_in [31:0] $end
$var wire 1 # read_en $end
$var wire 1 $ rst_n $end
$var wire 1 % write_en $end
$var wire 1 & full $end
$var wire 1 ' empty $end
$var parameter 32 ( DATA_WIDTH $end
$var parameter 32 ) DEPTH $end
$var parameter 32 * PTR_W $end
$var reg 32 + data_out [31:0] $end
$var reg 5 , read_ptr [4:0] $end
$var reg 5 - write_ptr [4:0] $end
$upscope $end
$enddefinitions $end
$comment Show the parameter values. $end
$dumpall
b101 *
b100000 )
b100000 (
$end
#0
$dumpvars
bx -
bx ,
bx +
x'
x&
z%
z$
z#
bz "
1!
$end
#5
0!
#10
0&
1'
b0 ,
b0 -
1!
1$
#15
0!
#20
1!
0$
#25
0!
#30
b1 -
1!
b11 "
1%
0'
#35
0!
#40
b1 ,
b11 +
b10 -
1!
b101 "
1#
#45
0!
#50
b10 ,
b101 +
b11 -
1!
b1001 "
#55
0!
#60
b11 ,
b1001 +
b100 -
1!
b10 "
#65
0!
#70
1'
b100 ,
b10 +
1!
0%
